{
  "routes": [
    {
      "name": "Amsterdam Canal Ring",
      "description": "A gentle loop through Amsterdam's historic canal district. Cobbled bridges, houseboats, and century-old merchant facades at every turn.",
      "location_type": "city",
      "country": "Netherlands",
      "region": "Noord-Holland",
      "difficulty": "flat",
      "total_distance_km": 12.4,
      "elevation_gain_m": 8,
      "sort_order": 1,
      "active": true,
      "thumbnail_url": null,
      "youtube_fallback_id": null,
      "waypoints": [
        { "lat": 52.3676, "lng": 4.9041, "heading": 312, "pitch": -2, "pano_id": null, "distance_from_start_m": 0 },
        { "lat": 52.3689, "lng": 4.9028, "heading": 318, "pitch": -1, "pano_id": null, "distance_from_start_m": 47 },
        { "lat": 52.3701, "lng": 4.9012, "heading": 305, "pitch": -2, "pano_id": null, "distance_from_start_m": 96 },
        { "lat": 52.3714, "lng": 4.9001, "heading": 298, "pitch": -1, "pano_id": null, "distance_from_start_m": 143 },
        { "lat": 52.3726, "lng": 4.8989, "heading": 310, "pitch": -2, "pano_id": null, "distance_from_start_m": 192 },
        { "lat": 52.3739, "lng": 4.8975, "heading": 322, "pitch": -1, "pano_id": null, "distance_from_start_m": 241 },
        { "lat": 52.3752, "lng": 4.8960, "heading": 315, "pitch": -2, "pano_id": null, "distance_from_start_m": 290 },
        { "lat": 52.3764, "lng": 4.8948, "heading": 308, "pitch": -1, "pano_id": null, "distance_from_start_m": 339 },
        { "lat": 52.3777, "lng": 4.8937, "heading": 295, "pitch": -2, "pano_id": null, "distance_from_start_m": 388 },
        { "lat": 52.3789, "lng": 4.8928, "heading": 288, "pitch": -1, "pano_id": null, "distance_from_start_m": 437 }
      ]
    },
    {
      "name": "Col du Tourmalet",
      "description": "The most climbed mountain pass in Tour de France history. A legendary 19km ascent through the Pyrenees with sweeping valley views.",
      "location_type": "mountain",
      "country": "France",
      "region": "Hautes-Pyrénées",
      "difficulty": "hilly",
      "total_distance_km": 19.0,
      "elevation_gain_m": 1404,
      "sort_order": 2,
      "active": true,
      "thumbnail_url": null,
      "youtube_fallback_id": null,
      "waypoints": [
        { "lat": 42.9001, "lng": 0.1423, "heading": 215, "pitch": 4, "pano_id": null, "distance_from_start_m": 0 },
        { "lat": 42.8983, "lng": 0.1408, "heading": 220, "pitch": 5, "pano_id": null, "distance_from_start_m": 52 },
        { "lat": 42.8964, "lng": 0.1394, "heading": 218, "pitch": 6, "pano_id": null, "distance_from_start_m": 104 },
        { "lat": 42.8946, "lng": 0.1381, "heading": 222, "pitch": 6, "pano_id": null, "distance_from_start_m": 156 },
        { "lat": 42.8928, "lng": 0.1369, "heading": 216, "pitch": 7, "pano_id": null, "distance_from_start_m": 208 },
        { "lat": 42.8910, "lng": 0.1358, "heading": 210, "pitch": 7, "pano_id": null, "distance_from_start_m": 260 },
        { "lat": 42.8892, "lng": 0.1348, "heading": 205, "pitch": 8, "pano_id": null, "distance_from_start_m": 312 },
        { "lat": 42.8874, "lng": 0.1340, "heading": 198, "pitch": 8, "pano_id": null, "distance_from_start_m": 364 },
        { "lat": 42.8856, "lng": 0.1334, "heading": 192, "pitch": 9, "pano_id": null, "distance_from_start_m": 416 },
        { "lat": 42.8838, "lng": 0.1330, "heading": 185, "pitch": 9, "pano_id": null, "distance_from_start_m": 468 }
      ]
    },
    {
      "name": "Kyoto Arashiyama",
      "description": "Ancient temples, bamboo groves, and the Oi River. A serene and beautiful loop through Kyoto's most scenic western district.",
      "location_type": "forest",
      "country": "Japan",
      "region": "Kyoto Prefecture",
      "difficulty": "flat",
      "total_distance_km": 8.2,
      "elevation_gain_m": 42,
      "sort_order": 3,
      "active": true,
      "thumbnail_url": null,
      "youtube_fallback_id": null,
      "waypoints": [
        { "lat": 35.0094, "lng": 135.6711, "heading": 72, "pitch": -1, "pano_id": null, "distance_from_start_m": 0 },
        { "lat": 35.0097, "lng": 135.6723, "heading": 78, "pitch": -1, "pano_id": null, "distance_from_start_m": 45 },
        { "lat": 35.0100, "lng": 135.6735, "heading": 82, "pitch": -2, "pano_id": null, "distance_from_start_m": 90 },
        { "lat": 35.0103, "lng": 135.6748, "heading": 85, "pitch": -1, "pano_id": null, "distance_from_start_m": 135 },
        { "lat": 35.0105, "lng": 135.6761, "heading": 79, "pitch": -1, "pano_id": null, "distance_from_start_m": 180 },
        { "lat": 35.0107, "lng": 135.6774, "heading": 76, "pitch": -2, "pano_id": null, "distance_from_start_m": 225 },
        { "lat": 35.0109, "lng": 135.6787, "heading": 73, "pitch": -1, "pano_id": null, "distance_from_start_m": 270 },
        { "lat": 35.0110, "lng": 135.6800, "heading": 70, "pitch": -1, "pano_id": null, "distance_from_start_m": 315 },
        { "lat": 35.0111, "lng": 135.6813, "heading": 68, "pitch": -2, "pano_id": null, "distance_from_start_m": 360 },
        { "lat": 35.0112, "lng": 135.6826, "heading": 65, "pitch": -1, "pano_id": null, "distance_from_start_m": 405 }
      ]
    },
    {
      "name": "Vancouver Sea to Sky",
      "description": "The iconic Highway 99 corridor from Horseshoe Bay northward — ocean on one side, Coast Mountains on the other. One of the most dramatic cycling roads in North America.",
      "location_type": "coastal",
      "country": "Canada",
      "region": "British Columbia",
      "difficulty": "rolling",
      "total_distance_km": 20.5,
      "elevation_gain_m": 312,
      "sort_order": 4,
      "active": true,
      "thumbnail_url": null,
      "youtube_fallback_id": null,
      "waypoints": [
        { "lat": 49.3741, "lng": -123.2694, "heading": 338, "pitch": -1, "pano_id": null, "distance_from_start_m": 0 },
        { "lat": 49.3762, "lng": -123.2708, "heading": 335, "pitch": -2, "pano_id": null, "distance_from_start_m": 53 },
        { "lat": 49.3784, "lng": -123.2720, "heading": 340, "pitch": -1, "pano_id": null, "distance_from_start_m": 106 },
        { "lat": 49.3805, "lng": -123.2730, "heading": 344, "pitch": 0, "pano_id": null, "distance_from_start_m": 159 },
        { "lat": 49.3827, "lng": -123.2739, "heading": 348, "pitch": 1, "pano_id": null, "distance_from_start_m": 212 },
        { "lat": 49.3849, "lng": -123.2746, "heading": 352, "pitch": 2, "pano_id": null, "distance_from_start_m": 265 },
        { "lat": 49.3871, "lng": -123.2751, "heading": 355, "pitch": 2, "pano_id": null, "distance_from_start_m": 318 },
        { "lat": 49.3893, "lng": -123.2754, "heading": 358, "pitch": 1, "pano_id": null, "distance_from_start_m": 371 },
        { "lat": 49.3915, "lng": -123.2756, "heading": 1, "pitch": 0, "pano_id": null, "distance_from_start_m": 424 },
        { "lat": 49.3937, "lng": -123.2756, "heading": 4, "pitch": -1, "pano_id": null, "distance_from_start_m": 477 }
      ]
    },
    {
      "name": "New York Central Park",
      "description": "The full 10km loop of Central Park's main drive. An urban classic past Bethesda Fountain, the reservoir, and Harlem Hill.",
      "location_type": "city",
      "country": "United States",
      "region": "New York",
      "difficulty": "rolling",
      "total_distance_km": 9.7,
      "elevation_gain_m": 78,
      "sort_order": 5,
      "active": true,
      "thumbnail_url": null,
      "youtube_fallback_id": null,
      "waypoints": [
        { "lat": 40.7679, "lng": -73.9762, "heading": 175, "pitch": -1, "pano_id": null, "distance_from_start_m": 0 },
        { "lat": 40.7661, "lng": -73.9764, "heading": 178, "pitch": -1, "pano_id": null, "distance_from_start_m": 48 },
        { "lat": 40.7643, "lng": -73.9764, "heading": 180, "pitch": 0, "pano_id": null, "distance_from_start_m": 96 },
        { "lat": 40.7625, "lng": -73.9763, "heading": 182, "pitch": 1, "pano_id": null, "distance_from_start_m": 144 },
        { "lat": 40.7607, "lng": -73.9760, "heading": 185, "pitch": 2, "pano_id": null, "distance_from_start_m": 192 },
        { "lat": 40.7589, "lng": -73.9756, "heading": 188, "pitch": 2, "pano_id": null, "distance_from_start_m": 240 },
        { "lat": 40.7571, "lng": -73.9750, "heading": 192, "pitch": 1, "pano_id": null, "distance_from_start_m": 288 },
        { "lat": 40.7554, "lng": -73.9742, "heading": 196, "pitch": 0, "pano_id": null, "distance_from_start_m": 336 },
        { "lat": 40.7537, "lng": -73.9733, "heading": 200, "pitch": -1, "pano_id": null, "distance_from_start_m": 384 },
        { "lat": 40.7520, "lng": -73.9722, "heading": 204, "pitch": -1, "pano_id": null, "distance_from_start_m": 432 }
      ]
    },
    {
      "name": "Mallorca Sa Calobra",
      "description": "One of cycling's most iconic climbs. The Nus de sa Corbata — a 270° loop-the-loop turn — and spectacular Mediterranean cliffs. Strava's most-ridden iconic climb.",
      "location_type": "mountain",
      "country": "Spain",
      "region": "Balearic Islands",
      "difficulty": "hilly",
      "total_distance_km": 9.4,
      "elevation_gain_m": 682,
      "sort_order": 6,
      "active": true,
      "thumbnail_url": null,
      "youtube_fallback_id": null,
      "waypoints": [
        { "lat": 39.8519, "lng": 2.7991, "heading": 158, "pitch": 5, "pano_id": null, "distance_from_start_m": 0 },
        { "lat": 39.8501, "lng": 2.7998, "heading": 162, "pitch": 6, "pano_id": null, "distance_from_start_m": 51 },
        { "lat": 39.8483, "lng": 2.8006, "heading": 165, "pitch": 7, "pano_id": null, "distance_from_start_m": 102 },
        { "lat": 39.8465, "lng": 2.8015, "heading": 168, "pitch": 7, "pano_id": null, "distance_from_start_m": 153 },
        { "lat": 39.8447, "lng": 2.8025, "heading": 172, "pitch": 8, "pano_id": null, "distance_from_start_m": 204 },
        { "lat": 39.8429, "lng": 2.8036, "heading": 176, "pitch": 8, "pano_id": null, "distance_from_start_m": 255 },
        { "lat": 39.8411, "lng": 2.8048, "heading": 180, "pitch": 9, "pano_id": null, "distance_from_start_m": 306 },
        { "lat": 39.8393, "lng": 2.8061, "heading": 184, "pitch": 9, "pano_id": null, "distance_from_start_m": 357 },
        { "lat": 39.8375, "lng": 2.8075, "heading": 188, "pitch": 10, "pano_id": null, "distance_from_start_m": 408 },
        { "lat": 39.8357, "lng": 2.8090, "heading": 192, "pitch": 10, "pano_id": null, "distance_from_start_m": 459 }
      ]
    }
  ]
}
